research_report/__init__.py
research_report/__init__.pyi
research_report/builder.py
research_report/builder.pyi
research_report/py.typed
research_report/records.py
research_report/records.pyi
research_report/report.py
research_report/report.pyi
research_report-1.0.0.dist-info/METADATA
research_report-1.0.0.dist-info/WHEEL
research_report-1.0.0.dist-info/top_level.txt
research_report-1.0.0.dist-info/RECORD
