Metadata-Version: 2.1
Name: research-report
Version: 1.0.0
Summary: A small library for convenient construction of experiments report
Home-page: https://github.com/TimurTimergalin/research_report
Author: TimurTimergalin
Author-email: tmtimergalin8080@gmail.com
Keywords: python report ipython
Classifier: Programming Language :: Python
Classifier: License :: OSI Approved :: MIT License
Classifier: Operating System :: OS Independent
Requires-Dist: reliable-finalizer >=1.0.0
Requires-Dist: ipython ~=8.29.0
